pyjats/__init__.py
pyjats/parser.py
pyjats/structures.py
pyjats-0.0.2.dist-info/LICENSE
pyjats-0.0.2.dist-info/WHEEL
pyjats-0.0.2.dist-info/METADATA
pyjats-0.0.2.dist-info/RECORD
